[
  {
    "id": "freq-author,authorId,channelId,content,id,timestamp",
    "type": "frequency-based",
    "confidence": 0.8,
    "description": "Repeating content: author,authorId,channelId,content,id,timestamp",
    "occurrences": 3,
    "firstSeen": 1770935752211,
    "lastSeen": 1771108552212,
    "metadata": {
      "source": "discord",
      "type": "message",
      "examples": [
        {
          "id": "1",
          "timestamp": "2026-02-12T22:35:52.211Z",
          "content": "おはよう",
          "author": "tndg16",
          "authorId": "123456789012345678",
          "channelId": "1471766005846905016"
        },
        {
          "id": "2",
          "timestamp": "2026-02-13T22:35:52.212Z",
          "content": "今日は何をする？",
          "author": "tndg16",
          "authorId": "123456789012345678",
          "channelId": "1471766005846905016"
        },
        {
          "id": "3",
          "timestamp": "2026-02-14T22:35:52.212Z",
          "content": "タスクを管理して",
          "author": "tndg16",
          "authorId": "123456789012345678",
          "channelId": "1471766005846905016"
        }
      ]
    },
    "category": "message",
    "frequency": 1.4999999913194444,
    "period": "day",
    "threshold": 3
  }
]
